egauge_async/__init__.py
egauge_async/client.py
egauge_async/data_models.py
egauge_async/exceptions.py
egauge_async/utils.py
egauge_async/json/__init__.py
egauge_async/json/auth.py
egauge_async/json/client.py
egauge_async/json/models.py
egauge_async/json/type_codes.py
egauge_async-0.3.0.dist-info/METADATA
egauge_async-0.3.0.dist-info/WHEEL
egauge_async-0.3.0.dist-info/licenses/LICENSE
egauge_async-0.3.0.dist-info/RECORD
