Metadata-Version: 2.4
Name: egauge-async
Version: 0.3.0
Summary: Async client for eGauge energy monitor (https://www.egauge.net)
Project-URL: Homepage, https://github.com/neggert/egauge-async
Author-email: Nic Eggert <nic@eggert.io>
License-Expression: GPL-3.0-only
License-File: LICENSE
Requires-Python: >=3.11
Requires-Dist: httpx<1.0.0,>=0.25.1
